latex_papersize
