Metadata-Version: 2.1
Name: latex-papersize
Version: 1.64
Summary: Change LaTeX paper size and margins to simulate any magnification
Home-page: http://ssb22.user.srcf.net/notes/#latex
Author: Silas S. Brown
Author-email: ssb22@cam.ac.uk
License: Apache 2
Platform: all
Classifier: Programming Language :: Python :: 2
Classifier: Programming Language :: Python :: 3
Classifier: License :: OSI Approved :: Apache Software License
Classifier: Operating System :: OS Independent
Requires-Python: >=2.0
License-File: LICENSE
